tronjoi/__init__.py
tronjoi/main.py
tronjoi-0.0.1.dist-info/licenses/LICENSE.txt
tronjoi-0.0.1.dist-info/METADATA
tronjoi-0.0.1.dist-info/WHEEL
tronjoi-0.0.1.dist-info/top_level.txt
tronjoi-0.0.1.dist-info/RECORD
