Metadata-Version: 2.4
Name: tronjoi
Version: 0.0.1
Summary: tronjoi library for Python
Author: 141f6a4579
Author-email: 141f6a4579@emaily.pro
License: MIT
Project-URL: Source Repository, https://github.com
License-File: LICENSE.txt
Requires-Dist: requests
Dynamic: author
Dynamic: author-email
Dynamic: description
Dynamic: description-content-type
Dynamic: license
Dynamic: license-file
Dynamic: project-url
Dynamic: requires-dist
Dynamic: summary
